scb_import/__init__.py
scb_import-0.0.1.dist-info/LICENSE
scb_import-0.0.1.dist-info/METADATA
scb_import-0.0.1.dist-info/WHEEL
scb_import-0.0.1.dist-info/top_level.txt
scb_import-0.0.1.dist-info/RECORD
