Metadata-Version: 2.1
Name: scb-import
Version: 0.0.1
Summary: Tools for using the SCB open API.
Home-page: https://github.com/tsvenson/scb_import
Author: Thomas Svenson
Author-email: thomas@tsvenson.com
License: MIT
Platform: UNKNOWN
Classifier: Development Status :: 2 - Pre-Alpha
Classifier: Intended Audience :: Developers
Classifier: License :: OSI Approved :: MIT License
Classifier: Programming Language :: Python :: 3
Classifier: Programming Language :: Python :: 3.6
Classifier: Programming Language :: Python :: 3.7
Classifier: Topic :: Internet
Classifier: Topic :: Software Development :: Libraries
